cutcutcodec-1.1.2.data/platlib/c_build.py
cutcutcodec-1.1.2.data/platlib/cutcutcodec/__init__.py
cutcutcodec-1.1.2.data/platlib/cutcutcodec/__main__.py
cutcutcodec-1.1.2.data/platlib/cutcutcodec/utils.py
cutcutcodec-1.1.2.data/platlib/cutcutcodec/core/__init__.py
cutcutcodec-1.1.2.data/platlib/cutcutcodec/core/exceptions.py
cutcutcodec-1.1.2.data/platlib/cutcutcodec/core/analysis/__init__.py
cutcutcodec-1.1.2.data/platlib/cutcutcodec/core/analysis/_helper_properties.py
cutcutcodec-1.1.2.data/platlib/cutcutcodec/core/analysis/ffprobe.py
cutcutcodec-1.1.2.data/platlib/cutcutcodec/core/analysis/audio/__init__.py
cutcutcodec-1.1.2.data/platlib/cutcutcodec/core/analysis/audio/properties/__init__.py
cutcutcodec-1.1.2.data/platlib/cutcutcodec/core/analysis/audio/properties/duration.py
cutcutcodec-1.1.2.data/platlib/cutcutcodec/core/analysis/graph/__init__.py
cutcutcodec-1.1.2.data/platlib/cutcutcodec/core/analysis/graph/find.py
cutcutcodec-1.1.2.data/platlib/cutcutcodec/core/analysis/graph/time_backprop.py
cutcutcodec-1.1.2.data/platlib/cutcutcodec/core/analysis/stream/__init__.py
cutcutcodec-1.1.2.data/platlib/cutcutcodec/core/analysis/stream/rate_audio.py
cutcutcodec-1.1.2.data/platlib/cutcutcodec/core/analysis/stream/rate_video.py
cutcutcodec-1.1.2.data/platlib/cutcutcodec/core/analysis/stream/shape.py
cutcutcodec-1.1.2.data/platlib/cutcutcodec/core/analysis/stream/time_backprop.py
cutcutcodec-1.1.2.data/platlib/cutcutcodec/core/analysis/video/__init__.py
cutcutcodec-1.1.2.data/platlib/cutcutcodec/core/analysis/video/properties/__init__.py
cutcutcodec-1.1.2.data/platlib/cutcutcodec/core/analysis/video/properties/duration.py
cutcutcodec-1.1.2.data/platlib/cutcutcodec/core/analysis/video/properties/nb_frames.py
cutcutcodec-1.1.2.data/platlib/cutcutcodec/core/analysis/video/properties/rate.py
cutcutcodec-1.1.2.data/platlib/cutcutcodec/core/analysis/video/properties/timestamps.py
cutcutcodec-1.1.2.data/platlib/cutcutcodec/core/classes/__init__.py
cutcutcodec-1.1.2.dist-info/LICENSE
cutcutcodec-1.1.2.dist-info/METADATA
cutcutcodec-1.1.2.dist-info/WHEEL
cutcutcodec-1.1.2.dist-info/entry_points.txt
cutcutcodec-1.1.2.dist-info/top_level.txt
cutcutcodec-1.1.2.dist-info/RECORD
