Metadata-Version: 2.1
Name: cutcutcodec
Version: 1.1.2
Summary: video editing software
Author-email: "Robin RICHARD (robinechuca)" <serveurpython.oz@gmail.com>
Maintainer-email: "Robin RICHARD (robinechuca)" <serveurpython.oz@gmail.com>
License: Copyright © 2023 Robin RICHARD
Project-URL: Homepage, https://framagit.org/robinechuca/cutcutcodec/-/blob/main/README.rst
Project-URL: Documentation, https://cutcutcodec.readthedocs.io/latest/
Project-URL: Repository, https://framagit.org/robinechuca/cutcutcodec/
Keywords: audio,effect,equation,ffmpeg,filtering,fractal,graph,graphical interface,gui,movie,open source,video editing
Classifier: Development Status :: 5 - Production/Stable
Classifier: Environment :: GPU
Classifier: Environment :: X11 Applications :: Qt
Classifier: Intended Audience :: Developers
Classifier: Intended Audience :: Education
Classifier: Intended Audience :: End Users/Desktop
Classifier: Intended Audience :: Science/Research
Classifier: License :: OSI Approved :: MIT License
Classifier: Natural Language :: English
Classifier: Operating System :: POSIX :: Linux
Classifier: Programming Language :: C
Classifier: Programming Language :: Python :: 3.11
Classifier: Programming Language :: Python :: 3.12
Classifier: Programming Language :: Python :: 3.13
Classifier: Topic :: Multimedia :: Graphics :: Editors
Classifier: Topic :: Multimedia :: Graphics :: Graphics Conversion
Classifier: Topic :: Multimedia :: Sound/Audio :: Analysis
Classifier: Topic :: Multimedia :: Sound/Audio :: Conversion
Classifier: Topic :: Multimedia :: Sound/Audio :: Editors
Classifier: Topic :: Multimedia :: Sound/Audio :: Mixers
Classifier: Topic :: Multimedia :: Sound/Audio :: Players
Classifier: Topic :: Multimedia :: Sound/Audio :: Sound Synthesis
Classifier: Topic :: Multimedia :: Video :: Conversion
Classifier: Topic :: Multimedia :: Video :: Display
Classifier: Topic :: Multimedia :: Video :: Non-Linear Editor
Classifier: Topic :: Scientific/Engineering :: Artificial Intelligence
Classifier: Topic :: Scientific/Engineering :: Image Processing
Classifier: Topic :: Scientific/Engineering :: Image Recognition
Classifier: Topic :: Scientific/Engineering :: Information Analysis
Classifier: Topic :: Scientific/Engineering :: Mathematics
Classifier: Topic :: Software Development :: Code Generators
Requires-Python: <3.14,>=3.11
License-File: LICENSE
Requires-Dist: av
Requires-Dist: black
Requires-Dist: cairosvg
Requires-Dist: click
Requires-Dist: lightning
Requires-Dist: networkx>=3.0
Requires-Dist: numpy>=2.0
Requires-Dist: opencv-contrib-python-headless
Requires-Dist: pip>=23.0
Requires-Dist: sympy>=1.10
Requires-Dist: torch>=2.1
Requires-Dist: tqdm
Requires-Dist: unidecode
Provides-Extra: doc
Requires-Dist: ipykernel; extra == "doc"
Requires-Dist: nbsphinx; extra == "doc"
Requires-Dist: pandoc; extra == "doc"
Requires-Dist: qtpy; extra == "doc"
Requires-Dist: qtpynodeeditor>=0.3.1; extra == "doc"
Requires-Dist: recommonmark; extra == "doc"
Requires-Dist: sphinx; extra == "doc"
Requires-Dist: sphinx-copybutton; extra == "doc"
Requires-Dist: sphinx-inline-tabs; extra == "doc"
Requires-Dist: sphinx-rtd-dark-mode; extra == "doc"
Requires-Dist: sphinx-rtd-theme; extra == "doc"
Requires-Dist: sphinxcontrib-video; extra == "doc"
Requires-Dist: sphinxext-opengraph; extra == "doc"
Provides-Extra: gui
Requires-Dist: matplotlib; extra == "gui"
Requires-Dist: notebook; extra == "gui"
Requires-Dist: pdoc3; extra == "gui"
Requires-Dist: pyqt6; extra == "gui"
Requires-Dist: pyqtgraph>=0.3.1; extra == "gui"
Requires-Dist: qtpy; extra == "gui"
Requires-Dist: qtpynodeeditor>=0.3.1; extra == "gui"
Provides-Extra: test
Requires-Dist: pydocstyle<=6.1.1; extra == "test"
Requires-Dist: pylama[all,toml]; extra == "test"
Requires-Dist: pytest; extra == "test"
